Metadata-Version: 2.4
Name: djangochan
Version: 0.1.0
Summary: Django-powered image/textboard engine.
Author-email: konfou <mail@konfou.xyz>
License-Expression: MIT
Project-URL: Homepage, https://github.com/konfou/djangochan
Project-URL: Issues, https://github.com/konfou/djangochan/issues
Keywords: django,imageboard,textboard,htmx,rest-framework
Classifier: Development Status :: 3 - Alpha
Classifier: Framework :: Django
Classifier: Framework :: Django :: 6.0
Requires-Python: >=3.10
License-File: LICENSE
Requires-Dist: Django
Requires-Dist: django-environ
Requires-Dist: django-precise-bbcode
Requires-Dist: django-simple-math-captcha
Requires-Dist: djangorestframework
Requires-Dist: passlib
Requires-Dist: sorl-thumbnail
Dynamic: license-file
